sql_to_odata/__init__.py
sql_to_odata-0.3.1.dist-info/LICENSE
sql_to_odata-0.3.1.dist-info/METADATA
sql_to_odata-0.3.1.dist-info/WHEEL
sql_to_odata-0.3.1.dist-info/RECORD
