Metadata-Version: 2.1
Name: sql-to-odata
Version: 0.3.1
Summary: Tools to facilitate adding an OData interface in front of a SQL database.
Home-page: https://github.com/lordjabez/sql-to-odata
License: MIT-0
Author: Judson Neer
Author-email: judson.neer@gmail.com
Requires-Python: >=3.8.1,<3.13
Classifier: License :: OSI Approved
Classifier: Programming Language :: Python :: 3
Classifier: Programming Language :: Python :: 3.9
Classifier: Programming Language :: Python :: 3.10
Classifier: Programming Language :: Python :: 3.11
Classifier: Programming Language :: Python :: 3.12
Requires-Dist: ujson (>=5.9.0,<6.0.0)
Project-URL: Repository, https://github.com/lordjabez/sql-to-odata
